{"origin": "fussballdaten", "year": 2022, "league_key": "frankreich", "season": "2021/2022", "matchday": "7", "link": "https://www.fussballdaten.de/frankreich/2022/7/angers-olmarseille/", "league_name": "Ligue 1", "date": "22.09.2021", "home_key": "sco-angers", "home_name": "SCO Angers", "home_short": "Angers", "away_key": "olympique-marseille", "away_name": "Olympique Marseille", "away_short": "Ol. Marseille", "home_goals": "0", "away_goals": "0", "home_goals_ht": "0", "away_goals_ht": "0", "home_possesion": 41.0, "away_possesion": 59.0, "home_attemps": 1.0, "away_attemps": 1.0, "home_missed": 8.0, "away_missed": 5.0, "home_offsite": 1.0, "away_offsite": 1.0, "home_held": 1.0, "away_held": 1.0, "home_fouls": 9.0, "away_fouls": 7.0, "home_passes": 85.7, "away_passes": 89.0, "home_yellow": 1.0, "away_yellow": 3.0, "home_red": 0.0, "away_red": 0.0, "home_players": "paul-bernardoni,vincent-manceau,ismael-traore-47527,romain-thomas,jimmy-cabot,batista-mendy,pierrick-capelle,enzo-ebosse,azzedine-ounahi,stephane-bahoken,angelo-fulgini", "away_players": "pau-lopez,duje-\u0106aleta-car,leonardo-balerdi,jordan-amavi,pol-lirola,boubacar-kamara,valentin-rongier,amine-harit,gerson-santos-da-silva,cheikh-bamba-dieng,luis-henrique-tomaz-de-lima", "home_tactic": "3-4-1-2", "away_tactic": "3-4-3"}