{"origin": "fussballdaten", "year": 2018, "league_key": "frankreich", "season": "2017/2018", "matchday": "25", "link": "https://www.fussballdaten.de/frankreich/2018/25/nantes-lille/", "league_name": "Ligue 1", "date": "11.02.2018", "home_key": "fc-nantes", "home_name": "FC Nantes", "home_short": "Nantes", "away_key": "osc-lille", "away_name": "OSC Lille", "away_short": "Lille", "home_goals": "2", "away_goals": "2", "home_goals_ht": "1", "away_goals_ht": "0", "home_possesion": 36.0, "away_possesion": 64.0, "home_attemps": 6.0, "away_attemps": 4.0, "home_missed": 11.0, "away_missed": 1.0, "home_freekicks": 11.0, "away_freekicks": 12.0, "home_corners": 5.0, "away_corners": 7.0, "home_offsite": 3.0, "away_offsite": 0.0, "home_held": 2.0, "away_held": 2.0, "home_fouls": 9.0, "away_fouls": 11.0, "home_rating": 3.3, "away_rating": 3.6, "home_tackles": 51.4, "away_tackles": 48.6, "home_passes": 76.9, "away_passes": 83.1, "home_yellow": 0.0, "away_yellow": 1.0, "home_red": 0.0, "away_red": 0.0, "home_players": "ciprian-t\u0103t\u0103ru\u0219anu,leo-dubois,david-alcibiade,koffi-djidji,lucas-pedro-alves-de-lima,abdoulaye-toure,andrei-girotto,jules-iloki,valentin-rongier,adrien-thomasson,emiliano-sala", "away_players": "mike-maignan,edgar-ie,kouadio-dabila,junior-osmar-ignacio-alonso-mujica,fode-ballo-toure,thiago-maia,ibrahim-amadou,thiago-mendes,anwar-el-ghazi,lebo-mothiba,yassine-benzia", "home_tactic": "4-2-3-1", "away_tactic": "4-3-3"}