{"standings": [{"origin": "fussballdaten", "year": 2017, "league_key": "england", "season": "2016/2017", "league_name": "Premier League", "matchday": "16", "place": "1", "team_key": "fc-chelsea", "team_name": "Chelsea", "points": "40", "goals": "34", "against": "11"}, {"origin": "fussballdaten", "year": 2017, "league_key": "england", "season": "2016/2017", "league_name": "Premier League", "matchday": "16", "place": "2", "team_key": "fc-liverpool", "team_name": "Liverpool", "points": "34", "goals": "40", "against": "20"}, {"origin": "fussballdaten", "year": 2017, "league_key": "england", "season": "2016/2017", "league_name": "Premier League", "matchday": "16", "place": "3", "team_key": "fc-arsenal", "team_name": "Arsenal", "points": "34", "goals": "37", "against": "17"}, {"origin": "fussballdaten", "year": 2017, "league_key": "england", "season": "2016/2017", "league_name": "Premier League", "matchday": "16", "place": "4", "team_key": "manchester-city", "team_name": "Man. City", "points": "33", "goals": "34", "against": "19"}, {"origin": "fussballdaten", "year": 2017, "league_key": "england", "season": "2016/2017", "league_name": "Premier League", "matchday": "16", "place": "5", "team_key": "tottenham-hotspur", "team_name": "Tottenham", "points": "30", "goals": "27", "against": "11"}, {"origin": "fussballdaten", "year": 2017, "league_key": "england", "season": "2016/2017", "league_name": "Premier League", "matchday": "16", "place": "6", "team_key": "manchester-united", "team_name": "Man. United", "points": "27", "goals": "22", "against": "17"}, {"origin": "fussballdaten", "year": 2017, "league_key": "england", "season": "2016/2017", "league_name": "Premier League", "matchday": "16", "place": "7", "team_key": "west-bromwich-albion", "team_name": "West Brom", "points": "23", "goals": "23", "against": "19"}, {"origin": "fussballdaten", "year": 2017, "league_key": "england", "season": "2016/2017", "league_name": "Premier League", "matchday": "16", "place": "8", "team_key": "fc-everton", "team_name": "Everton", "points": "23", "goals": "21", "against": "20"}, {"origin": "fussballdaten", "year": 2017, "league_key": "england", "season": "2016/2017", "league_name": "Premier League", "matchday": "16", "place": "9", "team_key": "fc-southampton", "team_name": "Southampton", "points": "21", "goals": "14", "against": "15"}, {"origin": "fussballdaten", "year": 2017, "league_key": "england", "season": "2016/2017", "league_name": "Premier League", "matchday": "16", "place": "10", "team_key": "afc-bournemouth", "team_name": "Bournemouth", "points": "21", "goals": "22", "against": "25"}, {"origin": "fussballdaten", "year": 2017, "league_key": "england", "season": "2016/2017", "league_name": "Premier League", "matchday": "16", "place": "11", "team_key": "fc-watford", "team_name": "Watford", "points": "21", "goals": "21", "against": "28"}, {"origin": "fussballdaten", "year": 2017, "league_key": "england", "season": "2016/2017", "league_name": "Premier League", "matchday": "16", "place": "12", "team_key": "stoke-city", "team_name": "Stoke City", "points": "20", "goals": "17", "against": "22"}, {"origin": "fussballdaten", "year": 2017, "league_key": "england", "season": "2016/2017", "league_name": "Premier League", "matchday": "16", "place": "13", "team_key": "fc-burnley", "team_name": "Burnley", "points": "17", "goals": "15", "against": "26"}, {"origin": "fussballdaten", "year": 2017, "league_key": "england", "season": "2016/2017", "league_name": "Premier League", "matchday": "16", "place": "14", "team_key": "leicester-city", "team_name": "Leicester", "points": "16", "goals": "21", "against": "27"}, {"origin": "fussballdaten", "year": 2017, "league_key": "england", "season": "2016/2017", "league_name": "Premier League", "matchday": "16", "place": "15", "team_key": "west-ham-united", "team_name": "West Ham", "points": "16", "goals": "18", "against": "31"}, {"origin": "fussballdaten", "year": 2017, "league_key": "england", "season": "2016/2017", "league_name": "Premier League", "matchday": "16", "place": "16", "team_key": "crystal-palace", "team_name": "Crystal Palace", "points": "15", "goals": "28", "against": "31"}, {"origin": "fussballdaten", "year": 2017, "league_key": "england", "season": "2016/2017", "league_name": "Premier League", "matchday": "16", "place": "17", "team_key": "fc-middlesbrough", "team_name": "Middlesbrough", "points": "15", "goals": "13", "against": "19"}, {"origin": "fussballdaten", "year": 2017, "league_key": "england", "season": "2016/2017", "league_name": "Premier League", "matchday": "16", "place": "18", "team_key": "swansea-city", "team_name": "Swansea City", "points": "12", "goals": "20", "against": "34"}, {"origin": "fussballdaten", "year": 2017, "league_key": "england", "season": "2016/2017", "league_name": "Premier League", "matchday": "16", "place": "19", "team_key": "hull-city-afc", "team_name": "Hull City", "points": "12", "goals": "14", "against": "35"}, {"origin": "fussballdaten", "year": 2017, "league_key": "england", "season": "2016/2017", "league_name": "Premier League", "matchday": "16", "place": "20", "team_key": "afc-sunderland", "team_name": "Sunderland", "points": "11", "goals": "14", "against": "28"}]}