{"origin": "fussballdaten", "year": 2021, "league_key": "italien", "season": "2020/2021", "matchday": "17", "link": "https://www.fussballdaten.de/italien/2021/17/juventusturin-sassuolo/", "league_name": "Serie A", "date": "10.01.2021", "home_key": "juventus-turin", "home_name": "Juventus Turin", "home_short": "Juventus Turin", "away_key": "us-sassuolo-calcio", "away_name": "US Sassuolo Calcio", "away_short": "Sassuolo", "home_goals": "3", "away_goals": "1", "home_goals_ht": "0", "away_goals_ht": "0", "home_possesion": 57.0, "away_possesion": 43.0, "home_attemps": 6.0, "away_attemps": 3.0, "home_missed": 8.0, "away_missed": 5.0, "home_freekicks": 4.0, "away_freekicks": 11.0, "home_corners": 6.0, "away_corners": 3.0, "home_offsite": 0.0, "away_offsite": 1.0, "home_held": 2.0, "away_held": 2.0, "home_fouls": 11.0, "away_fouls": 3.0, "home_tackles": 78.3, "away_tackles": 88.2, "home_passes": 94.0, "away_passes": 90.9, "home_yellow": 4.0, "away_yellow": 4.0, "home_red": 0.0, "away_red": 1.0, "home_players": "wojciech-szcz\u0119sny,danilo-luiz-da-silva,leonardo-bonucci,merih-demiral,gianluca-frabotta,federico-chiesa,rodrigo-bentancur,arthur,weston-mckennie,paulo-dybala,cristiano-ronaldo", "away_players": "andrea-consigli,mert-muelduer,vlad-chiriche\u015f,gianmarco-ferrari,giorgos-kyriakopoulos,pedro-obiang,manuel-locatelli,gregoire-defrel,filip-\u0110uri\u010di\u0107,hamed-junior-traore,francesco-caputo", "home_tactic": "4-4-2", "away_tactic": "4-2-3-1"}