{"origin": "fussballdaten", "year": 2018, "league_key": "frankreich", "season": "2017/2018", "matchday": "13", "link": "https://www.fussballdaten.de/frankreich/2018/13/bordeaux-marseille/", "league_name": "Ligue 1", "date": "19.11.2017", "home_key": "girondins-bordeaux", "home_name": "Girondins Bordeaux", "home_short": "Bordeaux", "away_key": "olympique-marseille", "away_name": "Olympique Marseille", "away_short": "Ol. Marseille", "home_goals": "1", "away_goals": "1", "home_goals_ht": "1", "away_goals_ht": "0", "home_possesion": 41.0, "away_possesion": 59.0, "home_attemps": 3.0, "away_attemps": 3.0, "home_missed": 5.0, "away_missed": 7.0, "home_freekicks": 16.0, "away_freekicks": 18.0, "home_corners": 3.0, "away_corners": 6.0, "home_offsite": 1.0, "away_offsite": 0.0, "home_held": 2.0, "away_held": 2.0, "home_fouls": 17.0, "away_fouls": 16.0, "home_rating": 3.8, "away_rating": 3.2, "home_tackles": 41.7, "away_tackles": 58.3, "home_passes": 70.9, "away_passes": 83.5, "home_yellow": 4.0, "away_yellow": 4.0, "home_red": 0.0, "away_red": 0.0, "home_players": "benoit-costil,youssouf-sabaly,igor-lewczuk,jeremy-toulalan,theo-pellenard,lukas-lerager,otavio,younousse-sankhare,malcom-filipe-silva-de-oliveira,nicolas-de-preville,francois-kamano", "away_players": "steve-mandanda,hiroki-sakai,adil-rami,rolando,jordan-amavi,andre-zambo-anguissa,dimitri-payet,morgan-sanson,florian-thauvin,kostas-mitroglou,lucas-ocampos", "home_tactic": "4-3-3", "away_tactic": "4-3-3"}