{"origin": "fussballdaten", "year": 2019, "league_key": "spanien", "season": "2018/2019", "matchday": "14", "link": "https://www.fussballdaten.de/spanien/2019/14/realmadrid-valencia/", "league_name": "Primera Divisi\u00f3n", "date": "01.12.2018", "home_key": "real-madrid", "home_name": "Real Madrid", "home_short": "Real Madrid", "away_key": "fc-valencia", "away_name": "FC Valencia", "away_short": "Valencia", "home_goals": "2", "away_goals": "0", "home_goals_ht": "1", "away_goals_ht": "0", "home_possesion": 61.0, "away_possesion": 39.0, "home_attemps": 3.0, "away_attemps": 2.0, "home_missed": 6.0, "away_missed": 3.0, "home_freekicks": 13.0, "away_freekicks": 13.0, "home_corners": 2.0, "away_corners": 2.0, "home_offsite": 2.0, "away_offsite": 3.0, "home_held": 2.0, "away_held": 2.0, "home_fouls": 11.0, "away_fouls": 10.0, "home_rating": 2.9, "away_rating": 4.0, "home_tackles": 61.0, "away_tackles": 39.0, "home_passes": 89.8, "away_passes": 86.7, "home_yellow": 1.0, "away_yellow": 3.0, "home_red": 0.0, "away_red": 0.0, "home_players": "thibaut-courtois,carvajal,sergio-ramos,raphael-varane,reguilon,luka-modri\u0107,llorente,dani-ceballos,lucas-vazquez,karim-benzema,gareth-bale", "away_players": "neto,daniel-wass,ezequiel-garay,gabriel-paulista,gaya,carlos-soler,dani-parejo,francis-coquelin,goncalo-guedes,kevin-gameiro,santi-mina", "home_tactic": "4-3-3", "away_tactic": "4-4-2"}