{"origin": "fussballdaten", "year": 2020, "league_key": "spanien", "season": "2019/2020", "matchday": "29", "link": "https://www.fussballdaten.de/spanien/2020/29/fcbarcelona-leganes/", "league_name": "Primera Divisi\u00f3n", "date": "16.06.2020", "home_key": "fc-barcelona", "home_name": "FC Barcelona", "home_short": "FC Barcelona", "away_key": "cd-leganes", "away_name": "CD Leganes", "away_short": "Leganes", "home_goals": "2", "away_goals": "0", "home_goals_ht": "1", "away_goals_ht": "0", "home_possesion": 75.0, "away_possesion": 25.0, "home_attemps": 5.0, "away_attemps": 2.0, "home_missed": 3.0, "away_missed": 1.0, "home_freekicks": 18.0, "away_freekicks": 16.0, "home_corners": 3.0, "away_corners": 2.0, "home_offsite": 1.0, "away_offsite": 1.0, "home_held": 2.0, "away_held": 3.0, "home_fouls": 15.0, "away_fouls": 16.0, "home_yellow": 5.0, "away_yellow": 5.0, "home_red": 0.0, "away_red": 0.0, "home_players": "marc-andre-ter-stegen,sergi-roberto,gerard-pique,clement-lenglet,junior-firpo,ivan-rakiti\u0107,sergio-busquets,arthur,lionel-messi,antoine-griezmann,ansu-fati", "away_players": "pichu-cuellar,unai-bustinza-martinez,rodri-tarin,chidozie-awaziem,jonathan-silva,recio,ruben-perez,aitor-ruibal,roque-mesa,eraso,miguel-angel-guerrero", "home_tactic": "4-3-3", "away_tactic": "4-2-3-1"}