{"origin": "fussballdaten", "year": 2021, "league_key": "frankreich", "season": "2020/2021", "matchday": "4", "link": "https://www.fussballdaten.de/frankreich/2021/4/montpellier-angers/", "league_name": "Ligue 1", "date": "20.09.2020", "home_key": "hsc-montpellier", "home_name": "HSC Montpellier", "home_short": "Montpellier", "away_key": "sco-angers", "away_name": "SCO Angers", "away_short": "Angers", "home_goals": "4", "away_goals": "1", "home_goals_ht": "2", "away_goals_ht": "1", "home_possesion": 52.0, "away_possesion": 48.0, "home_attemps": 9.0, "away_attemps": 3.0, "home_missed": 3.0, "away_missed": 6.0, "home_freekicks": 5.0, "away_freekicks": 14.0, "home_corners": 6.0, "away_corners": 3.0, "home_offsite": 0.0, "away_offsite": 0.0, "home_held": 2.0, "away_held": 5.0, "home_fouls": 14.0, "away_fouls": 5.0, "home_yellow": 4.0, "away_yellow": 4.0, "home_red": 0.0, "away_red": 0.0, "home_players": "jonas-omlin,pedro-filipe-teodosio-mendes,nicolas-cozza,daniel-congre,arnaud-souquet,jordan-ferri,teji-savanier,damien-le-tallec,mihailo-risti\u0107,gaetan-laborde,andy-delort", "away_players": "paul-bernardoni,abdoulaye-bamba,ismael-traore-47527,mateo-pavlovi\u0107,enzo-ebosse,lassana-coulibaly,pierrick-capelle,angelo-fulgini,thomas-mangani,antonin-bobichon,stephane-bahoken", "home_tactic": "3-5-2", "away_tactic": "4-1-4-1"}