{"origin": "fussballdaten", "year": 2023, "league_key": "italien", "season": "2022/2023", "matchday": "17", "link": "https://www.fussballdaten.de/italien/2023/17/ssmonza191-intermailand/", "league_name": "Serie A", "date": "07.01.2023", "home_key": "ss-monza-1912", "home_name": "SS Monza 1912", "home_short": "SS Monza 191", "away_key": "inter-mailand", "away_name": "Inter Mailand", "away_short": "Inter Mailand", "home_goals": "2", "away_goals": "2", "home_goals_ht": "1", "away_goals_ht": "2", "home_possesion": 55.0, "away_possesion": 45.0, "home_attemps": 6.0, "away_attemps": 4.0, "home_missed": 6.0, "away_missed": 8.0, "home_offsite": 0.0, "away_offsite": 3.0, "home_held": 1.0, "away_held": 1.0, "home_fouls": 1.0, "away_fouls": 2.0, "home_passes": 82.8, "away_passes": 82.3, "home_yellow": 0.0, "away_yellow": 4.0, "home_red": 0.0, "away_red": 0.0, "home_players": "michele-di-gregorio,marlon-santos-da-silva-barbosa,pablo-mari,armando-izzo,samuele-birindelli,matteo-pessina,jose-machin,carlos-augusto,patrick-ciurria,dany-mota,andrea-petagna", "away_players": "andre-onana,milan-scaron-kriniar,francesco-acerbi,alessandro-bastoni,matteo-darmian,nicolo-barella,hakan-calhano\u011flu,henrikh-mkhitaryan,federico-dimarco,edin-d\u017eeko,lautaro-martinez", "home_tactic": "3-4-2-1", "away_tactic": "3-5-2"}