{"origin": "fussballdaten", "year": 2021, "league_key": "frankreich", "season": "2020/2021", "matchday": "9", "link": "https://www.fussballdaten.de/frankreich/2021/9/nantes-psg/", "league_name": "Ligue 1", "date": "31.10.2020", "home_key": "fc-nantes", "home_name": "FC Nantes", "home_short": "Nantes", "away_key": "paris-st-germain", "away_name": "Paris St. Germain", "away_short": "PSG", "home_goals": "0", "away_goals": "3", "home_goals_ht": "0", "away_goals_ht": "0", "home_possesion": 35.0, "away_possesion": 65.0, "home_attemps": 1.0, "away_attemps": 4.0, "home_missed": 3.0, "away_missed": 5.0, "home_freekicks": 17.0, "away_freekicks": 11.0, "home_corners": 2.0, "away_corners": 4.0, "home_offsite": 0.0, "away_offsite": 0.0, "home_held": 1.0, "away_held": 1.0, "home_fouls": 11.0, "away_fouls": 13.0, "home_yellow": 2.0, "away_yellow": 2.0, "home_red": 0.0, "away_red": 0.0, "home_players": "kader-bamba,alban-lafont,dennis-appiah,jean-charles-castelletto-319495,mehdi-abeid,charles-traore,chirivella,imran-louza,marcus-coco,ludovic-blas,moses-simon", "away_players": "randal-kolo-muani,keylor-navas,colin-dagba,danilo-pereira,abdou-diallo,mitchel-bakker,ander-herrera,idrissa-gueye,rafael-alcantara-do-nascimento,pablo-sarabia,moise-kean,kylian-mbappe", "home_tactic": "4-2-3-1", "away_tactic": "4-3-3"}