{"origin": "fussballdaten", "year": 2023, "league_key": "frankreich", "season": "2022/2023", "matchday": "12", "link": "https://www.fussballdaten.de/frankreich/2023/12/troyes-lorient/", "league_name": "Ligue 1", "date": "23.10.2022", "home_key": "es-troyes-ac", "home_name": "ES Troyes AC", "home_short": "Troyes", "away_key": "fc-lorient", "away_name": "FC Lorient", "away_short": "Lorient", "home_goals": "2", "away_goals": "2", "home_goals_ht": "1", "away_goals_ht": "0", "home_possesion": 43.0, "away_possesion": 57.0, "home_attemps": 5.0, "away_attemps": 6.0, "home_missed": 9.0, "away_missed": 15.0, "home_offsite": 2.0, "away_offsite": 2.0, "home_held": 3.0, "away_held": 3.0, "home_fouls": 8.0, "away_fouls": 9.0, "home_passes": 86.4, "away_passes": 88.1, "home_yellow": 3.0, "away_yellow": 3.0, "home_red": 0.0, "away_red": 0.0, "home_players": "mateusz-lis-474640,thierno-balde,jackson-porozo-vernaza,erik-palmer-brown,yoann-salmier,abdu-conte,rony-lopes,rominigue-kouame,xavier-chavalerin,wilson-odobert,mama-samba-balde", "away_players": "yvon-mvogo,theo-le-bris,julien-laporte,montassar-talbi,vincent-le-goff,bonke-innocent,enzo-le-fee,stephane-diarra,julien-ponceau,dango-aboubacar-faissal-ouattara,ibrahima-kone", "home_tactic": "5-4-1", "away_tactic": "4-2-3-1"}