{"origin": "fussballdaten", "year": 2018, "league_key": "england", "season": "2017/2018", "matchday": "29", "link": "https://www.fussballdaten.de/england/2018/29/brighton-arsenal/", "league_name": "Premier League", "date": "04.03.2018", "home_key": "brighton-and-hove-albion", "home_name": "Brighton and Hove Albion", "home_short": "Brighton", "away_key": "fc-arsenal", "away_name": "FC Arsenal", "away_short": "Arsenal", "home_goals": "2", "away_goals": "1", "home_goals_ht": "2", "away_goals_ht": "1", "home_possesion": 32.0, "away_possesion": 68.0, "home_attemps": 6.0, "away_attemps": 7.0, "home_missed": 5.0, "away_missed": 2.0, "home_freekicks": 13.0, "away_freekicks": 20.0, "home_corners": 6.0, "away_corners": 11.0, "home_offsite": 6.0, "away_offsite": 1.0, "home_held": 6.0, "away_held": 6.0, "home_fouls": 14.0, "away_fouls": 13.0, "home_rating": 3.1, "away_rating": 3.2, "home_tackles": 47.0, "away_tackles": 53.0, "home_passes": 70.4, "away_passes": 86.1, "home_yellow": 3.0, "away_yellow": 3.0, "home_red": 0.0, "away_red": 0.0, "home_players": "mathew-ryan,matias-ezequiel-schelotto,shane-duffy,lewis-dunk,gaetan-bong,anthony-knockaert,dale-stephens,davy-proepper,jose-heriberto-izquierdo-mena,pascal-gross,glenn-murray", "away_players": "petr-cech,calum-chambers,shkodran-mustafi,laurent-koscielny,sead-kola-scaron-inac,jack-wilshere,granit-xhaka,alex-iwobi,mesut-oezil,henrikh-mkhitaryan,pierre-emerick-aubameyang", "home_tactic": "4-4-2", "away_tactic": "4-2-3-1"}