{"origin": "fussballdaten", "year": 2017, "league_key": "frankreich", "season": "2016/2017", "matchday": "19", "link": "https://www.fussballdaten.de/frankreich/2017/19/paris-lorient/", "league_name": "Ligue 1", "date": "21.12.2016", "home_key": "paris-st-germain", "home_name": "Paris St. Germain", "home_short": "PSG", "away_key": "fc-lorient", "away_name": "FC Lorient", "away_short": "Lorient", "home_goals": "5", "away_goals": "0", "home_goals_ht": "2", "away_goals_ht": "0", "home_possesion": 63.0, "away_possesion": 37.0, "home_attemps": 7.0, "away_attemps": 2.0, "home_missed": 9.0, "away_missed": 2.0, "home_freekicks": 9.0, "away_freekicks": 12.0, "home_corners": 13.0, "away_corners": 3.0, "home_offsite": 4.0, "away_offsite": 0.0, "home_held": 2.0, "away_held": 2.0, "home_fouls": 8.0, "away_fouls": 9.0, "home_tackles": 56.1, "away_tackles": 43.9, "home_passes": 93.7, "away_passes": 85.9, "home_yellow": 0.0, "away_yellow": 1.0, "home_red": 0.0, "away_red": 0.0, "home_players": "kevin-trapp,thomas-meunier,marcos-aoas-correa,thiago-silva,layvin-kurzawa,marco-verratti,thiago-motta,christopher-nkunku,lucas-moura,edinson-cavani,blaise-matuidi", "away_players": "paul-delecroix,erwin-koffi,zargo-toure,michael-ciani,vincent-le-goff,wesley-lautoa,sylvain-marveaux,arnold-mvuemba,walid-mesloub,majeed-waris,benjamin-moukandjo", "home_tactic": "4-3-3", "away_tactic": "4-1-4-1"}