{"origin": "fussballdaten", "year": 2017, "league_key": "england", "season": "2016/2017", "matchday": "10", "link": "https://www.fussballdaten.de/england/2017/10/palace-liverpool/", "league_name": "Premier League", "date": "29.10.2016", "home_key": "crystal-palace", "home_name": "Crystal Palace", "home_short": "Crystal Palace", "away_key": "fc-liverpool", "away_name": "FC Liverpool", "away_short": "Liverpool", "home_goals": "2", "away_goals": "4", "home_goals_ht": "2", "away_goals_ht": "3", "home_possesion": 40.0, "away_possesion": 60.0, "home_attemps": 6.0, "away_attemps": 10.0, "home_missed": 1.0, "away_missed": 4.0, "home_freekicks": 6.0, "away_freekicks": 19.0, "home_corners": 3.0, "away_corners": 3.0, "home_offsite": 4.0, "away_offsite": 1.0, "home_held": 6.0, "away_held": 6.0, "home_fouls": 15.0, "away_fouls": 5.0, "home_rating": 4.5, "away_rating": 2.7, "home_tackles": 47.7, "away_tackles": 52.3, "home_passes": 73.0, "away_passes": 76.6, "home_yellow": 1.0, "away_yellow": 2.0, "home_red": 0.0, "away_red": 0.0, "home_players": "steve-mandanda,joel-ward,james-tomkins,scott-dann,martin-kelly,james-mcarthur,joe-ledley,chung-yong-lee,yohan-cabaye,wilfried-zaha,christian-benteke", "away_players": "loris-karius,nathaniel-clyne,joel-matip,dejan-lovren,alberto-moreno,adam-lallana,jordan-henderson,emre-can,sadio-mane,roberto-firmino,philippe-coutinho", "home_tactic": "4-2-3-1", "away_tactic": "4-3-3"}