{"origin": "fussballdaten", "year": 2019, "league_key": "spanien", "season": "2018/2019", "matchday": "10", "link": "https://www.fussballdaten.de/spanien/2019/10/girona-vallecano/", "league_name": "Primera Divisi\u00f3n", "date": "27.10.2018", "home_key": "fc-girona", "home_name": "FC Girona", "home_short": "Girona", "away_key": "rayo-vallecano", "away_name": "Rayo Vallecano", "away_short": "Vallecano", "home_goals": "2", "away_goals": "1", "home_goals_ht": "2", "away_goals_ht": "0", "home_possesion": 44.0, "away_possesion": 56.0, "home_attemps": 6.0, "away_attemps": 5.0, "home_missed": 8.0, "away_missed": 5.0, "home_freekicks": 17.0, "away_freekicks": 14.0, "home_corners": 4.0, "away_corners": 7.0, "home_offsite": 3.0, "away_offsite": 2.0, "home_held": 4.0, "away_held": 4.0, "home_fouls": 11.0, "away_fouls": 15.0, "home_rating": 3.3, "away_rating": 3.8, "home_tackles": 48.4, "away_tackles": 52.2, "home_passes": 79.8, "away_passes": 82.1, "home_yellow": 1.0, "away_yellow": 3.0, "home_red": 1.0, "away_red": 0.0, "home_players": "bono,jonas-ramalho,bernardo-espinosa,juanpe,pedro-porro,pere-pons,borja-garcia-freire,douglas-luiz,francisco-aday-benitez-caraballo,portu,anthony-lozano", "away_players": "alberto-garcia,luis-advincula,alejandro-galvez,jordi-amat,alejandro-moreno-lopera,oscar-trejo,santi-comesana,giannelli-imbula,adrian-embarba,raul-de-tomas,gael-kakuta", "home_tactic": "3-5-2", "away_tactic": "4-3-3"}