{"origin": "fussballdaten", "year": 2021, "league_key": "england", "season": "2020/2021", "matchday": "10", "link": "https://www.fussballdaten.de/england/2021/10/southampton-manunited/", "league_name": "Premier League", "date": "29.11.2020", "home_key": "fc-southampton", "home_name": "FC Southampton", "home_short": "Southampton", "away_key": "manchester-united", "away_name": "Manchester United", "away_short": "Man. United", "home_goals": "2", "away_goals": "3", "home_goals_ht": "2", "away_goals_ht": "0", "home_possesion": 50.0, "away_possesion": 50.0, "home_attemps": 5.0, "away_attemps": 7.0, "home_missed": 2.0, "away_missed": 4.0, "home_freekicks": 12.0, "away_freekicks": 12.0, "home_corners": 5.0, "away_corners": 9.0, "home_offsite": 0.0, "away_offsite": 0.0, "home_held": 4.0, "away_held": 4.0, "home_fouls": 12.0, "away_fouls": 12.0, "home_tackles": 88.2, "away_tackles": 95.5, "home_passes": 85.5, "away_passes": 81.9, "home_yellow": 1.0, "away_yellow": 1.0, "home_red": 0.0, "away_red": 0.0, "home_players": "alex-mccarthy,kyle-walker-peters,jan-bednarek,jannik-vestergaard,ryan-bertrand,stuart-armstrong,james-ward-prowse,oriol-romeu,moussa-djenepo,theo-walcott,che-adams", "away_players": "david-de-gea,aaron-wan-bissaka,victor-lindeloef,harry-maguire,alex-telles,frederico-rodrigues-santos,nemanja-mati\u0107,donny-van-de-beek,bruno-miguel-borges-fernandes,marcus-rashford,mason-greenwood", "home_tactic": "4-4-2", "away_tactic": "4-3-1-2"}