{"origin": "fussballdaten", "year": 2017, "league_key": "2liga", "season": "2016/2017", "matchday": "21", "link": "https://www.fussballdaten.de/2liga/2017/21/tsv1860-nuernberg/", "league_name": "2. Bundesliga", "date": "20.02.2017", "home_key": "tsv-1860-muenchen", "home_name": "TSV 1860 M\u00fcnchen", "home_short": "TSV 1860", "away_key": "1-fc-nuernberg", "away_name": "1. FC N\u00fcrnberg", "away_short": "N\u00fcrnberg", "home_goals": "2", "away_goals": "0", "home_goals_ht": "2", "away_goals_ht": "0", "home_possesion": 51.0, "away_possesion": 49.0, "home_attemps": 5.0, "away_attemps": 0.0, "home_missed": 2.0, "away_missed": 4.0, "home_freekicks": 16.0, "away_freekicks": 16.0, "home_corners": 7.0, "away_corners": 1.0, "home_offsite": 0.0, "away_offsite": 0.0, "home_held": 0.0, "away_held": 3.0, "home_fouls": 16.0, "away_fouls": 15.0, "home_yellow": 3.0, "away_yellow": 3.0, "home_red": 0.0, "away_red": 0.0, "home_players": "stefan-ortega,sebastian-boenisch,abdoulaye-ba-47839,felix-uduokhai,maximilian-wittek,romuald-lacazette,kai-buelow,lumor,amilton,christian-gytkjaer,levent-aycicek", "away_players": "thorsten-kirschbaum,patrick-kammerbauer,lukas-muehl,even-hovland,dennis-lippert,ond\u0159ej-petrak,hanno-behrens,tobias-kempe,kevin-moehwald,abdelhamid-sabiri,rurik-gislason", "home_tactic": "3-4-3", "away_tactic": "4-2-3-1"}