{"origin": "fussballdaten", "year": 2018, "league_key": "2liga", "season": "2017/2018", "matchday": "23", "link": "https://www.fussballdaten.de/2liga/2018/23/heidenheim-bochum/", "league_name": "2. Bundesliga", "date": "16.02.2018", "home_key": "1-fc-heidenheim-1846", "home_name": "1. FC Heidenheim 1846", "home_short": "Heidenheim", "away_key": "vfl-bochum", "away_name": "VfL Bochum", "away_short": "VfL Bochum", "home_goals": "1", "away_goals": "0", "home_goals_ht": "1", "away_goals_ht": "0", "home_possesion": 35.0, "away_possesion": 65.0, "home_attemps": 2.0, "away_attemps": 7.0, "home_missed": 4.0, "away_missed": 6.0, "home_freekicks": 14.0, "away_freekicks": 24.0, "home_corners": 2.0, "away_corners": 9.0, "home_offsite": 0.0, "away_offsite": 0.0, "home_held": 7.0, "away_held": 1.0, "home_fouls": 24.0, "away_fouls": 11.0, "home_yellow": 2.0, "away_yellow": 4.0, "home_red": 0.0, "away_red": 0.0, "home_players": "kevin-mueller,robert-strauss,mathias-wittek,timo-beermann,arne-feick,marc-schnatterer,sebastian-griesbeck,marcel-titsch-rivero,maximilian-thiel,nikola-dovedan,john-verhoek", "away_players": "manuel-riemann,jan-gyamerah,patrick-fabian,tim-hoogland,danilo-soares,anthony-losilla,kevin-stoeger,robert-tesche,sidney-sam,lukas-hinterseer,robbie-kruse", "home_tactic": "4-4-1-1", "away_tactic": "4-3-3"}