{"origin": "fussballdaten", "year": 2021, "league_key": "italien", "season": "2020/2021", "matchday": "15", "link": "https://www.fussballdaten.de/italien/2021/15/benevento-acmailand/", "league_name": "Serie A", "date": "03.01.2021", "home_key": "benevento-calcio", "home_name": "Benevento Calcio", "home_short": "Benevento", "away_key": "ac-mailand", "away_name": "AC Mailand", "away_short": "AC Mailand", "home_goals": "0", "away_goals": "2", "home_goals_ht": "0", "away_goals_ht": "1", "home_possesion": 51.0, "away_possesion": 49.0, "home_attemps": 5.0, "away_attemps": 2.0, "home_missed": 7.0, "away_missed": 6.0, "home_freekicks": 16.0, "away_freekicks": 10.0, "home_corners": 12.0, "away_corners": 4.0, "home_offsite": 1.0, "away_offsite": 2.0, "home_held": 0.0, "away_held": 0.0, "home_fouls": 9.0, "away_fouls": 14.0, "home_tackles": 81.8, "away_tackles": 86.7, "home_passes": 83.8, "away_passes": 90.5, "home_yellow": 1.0, "away_yellow": 3.0, "home_red": 0.0, "away_red": 1.0, "home_players": "gianluca-caprari,lorenzo-montipo,gaetano-letizia,alessandro-tuia,kamil-glik,federico-barba,pasquale-schiattarella,perparim-hetemaj,artur-ioni\u021b\u0103,roberto-insigne,gianluca-caprari", "away_players": "gianluca-lapadula,gianluigi-donnarumma,davide-calabria,simon-kjaer,alessio-romagnoli,diogo-dalot,sandro-tonali,franck-kessie,brahim-diaz,alexis-saelemaekers,hakan-calhano\u011flu,ante-rebi\u0107,rafael-leao", "home_tactic": "4-3-2-1", "away_tactic": "4-2-3-1"}