{"standings": [{"origin": "fussballdaten", "year": 2021, "league_key": "bundesliga", "season": "2020/2021", "league_name": "Bundesliga", "matchday": "25", "place": "1", "team_key": "fc-bayern-muenchen", "team_name": "Bayern", "points": "58", "goals": "74", "against": "35"}, {"origin": "fussballdaten", "year": 2021, "league_key": "bundesliga", "season": "2020/2021", "league_name": "Bundesliga", "matchday": "25", "place": "2", "team_key": "rb-leipzig", "team_name": "RB Leipzig", "points": "54", "goals": "47", "against": "21"}, {"origin": "fussballdaten", "year": 2021, "league_key": "bundesliga", "season": "2020/2021", "league_name": "Bundesliga", "matchday": "25", "place": "3", "team_key": "vfl-wolfsburg", "team_name": "Wolfsburg", "points": "48", "goals": "43", "against": "21"}, {"origin": "fussballdaten", "year": 2021, "league_key": "bundesliga", "season": "2020/2021", "league_name": "Bundesliga", "matchday": "25", "place": "4", "team_key": "eintracht-frankfurt", "team_name": "Frankfurt", "points": "44", "goals": "48", "against": "34"}, {"origin": "fussballdaten", "year": 2021, "league_key": "bundesliga", "season": "2020/2021", "league_name": "Bundesliga", "matchday": "25", "place": "5", "team_key": "borussia-dortmund", "team_name": "Dortmund", "points": "42", "goals": "52", "against": "35"}, {"origin": "fussballdaten", "year": 2021, "league_key": "bundesliga", "season": "2020/2021", "league_name": "Bundesliga", "matchday": "25", "place": "6", "team_key": "bayer-leverkusen", "team_name": "Leverkusen", "points": "40", "goals": "43", "against": "28"}, {"origin": "fussballdaten", "year": 2021, "league_key": "bundesliga", "season": "2020/2021", "league_name": "Bundesliga", "matchday": "25", "place": "7", "team_key": "1-fc-union-berlin", "team_name": "Union Berlin", "points": "38", "goals": "38", "against": "27"}, {"origin": "fussballdaten", "year": 2021, "league_key": "bundesliga", "season": "2020/2021", "league_name": "Bundesliga", "matchday": "25", "place": "8", "team_key": "vfb-stuttgart", "team_name": "Stuttgart", "points": "36", "goals": "47", "against": "37"}, {"origin": "fussballdaten", "year": 2021, "league_key": "bundesliga", "season": "2020/2021", "league_name": "Bundesliga", "matchday": "25", "place": "9", "team_key": "sc-freiburg", "team_name": "Freiburg", "points": "34", "goals": "37", "against": "39"}, {"origin": "fussballdaten", "year": 2021, "league_key": "bundesliga", "season": "2020/2021", "league_name": "Bundesliga", "matchday": "25", "place": "10", "team_key": "borussia-moenchengladbach", "team_name": "M'gladbach", "points": "33", "goals": "41", "against": "40"}, {"origin": "fussballdaten", "year": 2021, "league_key": "bundesliga", "season": "2020/2021", "league_name": "Bundesliga", "matchday": "25", "place": "11", "team_key": "1899-hoffenheim", "team_name": "Hoffenheim", "points": "30", "goals": "39", "against": "43"}, {"origin": "fussballdaten", "year": 2021, "league_key": "bundesliga", "season": "2020/2021", "league_name": "Bundesliga", "matchday": "25", "place": "12", "team_key": "sv-werder-bremen", "team_name": "Bremen", "points": "30", "goals": "30", "against": "36"}, {"origin": "fussballdaten", "year": 2021, "league_key": "bundesliga", "season": "2020/2021", "league_name": "Bundesliga", "matchday": "25", "place": "13", "team_key": "fc-augsburg", "team_name": "Augsburg", "points": "29", "goals": "27", "against": "38"}, {"origin": "fussballdaten", "year": 2021, "league_key": "bundesliga", "season": "2020/2021", "league_name": "Bundesliga", "matchday": "25", "place": "14", "team_key": "1-fc-koeln", "team_name": "K\u00f6ln", "points": "22", "goals": "23", "against": "44"}, {"origin": "fussballdaten", "year": 2021, "league_key": "bundesliga", "season": "2020/2021", "league_name": "Bundesliga", "matchday": "25", "place": "15", "team_key": "arminia-bielefeld", "team_name": "Bielefeld", "points": "22", "goals": "20", "against": "44"}, {"origin": "fussballdaten", "year": 2021, "league_key": "bundesliga", "season": "2020/2021", "league_name": "Bundesliga", "matchday": "25", "place": "16", "team_key": "hertha-bsc", "team_name": "Hertha BSC", "points": "21", "goals": "28", "against": "45"}, {"origin": "fussballdaten", "year": 2021, "league_key": "bundesliga", "season": "2020/2021", "league_name": "Bundesliga", "matchday": "25", "place": "17", "team_key": "1-fsv-mainz-05", "team_name": "Mainz", "points": "21", "goals": "24", "against": "44"}, {"origin": "fussballdaten", "year": 2021, "league_key": "bundesliga", "season": "2020/2021", "league_name": "Bundesliga", "matchday": "25", "place": "18", "team_key": "fc-schalke-04", "team_name": "Schalke", "points": "10", "goals": "16", "against": "66"}]}