{"origin": "fussballdaten", "year": 2018, "league_key": "bundesliga", "season": "2017/2018", "matchday": "2", "link": "https://www.fussballdaten.de/bundesliga/2018/2/bremen-bayern/", "league_name": "Bundesliga", "date": "26.08.2017", "home_key": "sv-werder-bremen", "home_name": "SV Werder Bremen", "home_short": "Bremen", "away_key": "fc-bayern-muenchen", "away_name": "FC Bayern M\u00fcnchen", "away_short": "Bayern", "home_goals": "0", "away_goals": "2", "home_goals_ht": "0", "away_goals_ht": "0", "home_possesion": 31.0, "away_possesion": 69.0, "home_attemps": 0.0, "away_attemps": 8.0, "home_missed": 1.0, "away_missed": 8.0, "home_freekicks": 9.0, "away_freekicks": 8.0, "home_corners": 2.0, "away_corners": 8.0, "home_offsite": 0.0, "away_offsite": 0.0, "home_held": 6.0, "away_held": 6.0, "home_fouls": 8.0, "away_fouls": 9.0, "home_rating": 4.2, "away_rating": 2.9, "home_tackles": 48.3, "away_tackles": 51.7, "home_passes": 72.9, "away_passes": 89.5, "home_yellow": 1.0, "away_yellow": 1.0, "home_red": 0.0, "away_red": 0.0, "home_players": "ji\u0159i-pavlenka,robert-bauer,lamine-sane,milo-scaron-veljkovi\u0107,theodor-gebre-selassie,jerome-gondorf,maximilian-eggestein,thomas-delaney,ludwig-augustinsson,fin-bartels,max-kruse", "away_players": "manuel-neuer,joshua-kimmich,niklas-suele,mats-hummels,david-alaba,thiago-alcantara,corentin-tolisso,arturo-vidal,arjen-robben,robert-lewandowski,franck-ribery", "home_tactic": "3-5-2", "away_tactic": "4-1-2-3"}