{"origin": "fussballdaten", "year": 2019, "league_key": "2liga", "season": "2018/2019", "matchday": "10", "link": "https://www.fussballdaten.de/2liga/2019/10/heidenheim-magdeburg/", "league_name": "2. Bundesliga", "date": "20.10.2018", "home_key": "1-fc-heidenheim-1846", "home_name": "1. FC Heidenheim 1846", "home_short": "Heidenheim", "away_key": "1-fc-magdeburg", "away_name": "1. FC Magdeburg", "away_short": "Magdeburg", "home_goals": "3", "away_goals": "0", "home_goals_ht": "2", "away_goals_ht": "0", "home_possesion": 47.0, "away_possesion": 53.0, "home_attemps": 5.0, "away_attemps": 4.0, "home_missed": 0.0, "away_missed": 7.0, "home_freekicks": 16.0, "away_freekicks": 19.0, "home_corners": 2.0, "away_corners": 8.0, "home_offsite": 2.0, "away_offsite": 2.0, "home_held": 4.0, "away_held": 2.0, "home_fouls": 17.0, "away_fouls": 10.0, "home_yellow": 0.0, "away_yellow": 3.0, "home_red": 0.0, "away_red": 1.0, "home_players": "kevin-mueller,marnon-busch,patrick-mainka,timo-beermann,norman-theuerkauf,sebastian-griesbeck,niklas-dorsch,marc-schnatterer,robert-strauss,patrick-schmidt-47200,nikola-dovedan", "away_players": "alexander-brunst,tobias-mueller,dennis-erdmann,romain-bregerie,nils-butzen,bjoern-rother,aleksandar-ignjovski,nico-hammann,philip-tuerpitz,christian-beck,marcel-costly", "home_tactic": "4-2-2-2", "away_tactic": "3-4-3"}