{"origin": "fussballdaten", "year": 2021, "league_key": "bundesliga", "season": "2020/2021", "matchday": "19", "link": "https://www.fussballdaten.de/bundesliga/2021/19/stuttgart-mainz/", "league_name": "Bundesliga", "date": "29.01.2021", "home_key": "vfb-stuttgart", "home_name": "VfB Stuttgart", "home_short": "Stuttgart", "away_key": "1-fsv-mainz-05", "away_name": "1. FSV Mainz 05", "away_short": "Mainz", "home_goals": "2", "away_goals": "0", "home_goals_ht": "0", "away_goals_ht": "0", "home_possesion": 47.0, "away_possesion": 53.0, "home_attemps": 3.0, "away_attemps": 2.0, "home_missed": 4.0, "away_missed": 4.0, "home_freekicks": 19.0, "away_freekicks": 15.0, "home_corners": 2.0, "away_corners": 4.0, "home_offsite": 3.0, "away_offsite": 0.0, "home_held": 2.0, "away_held": 2.0, "home_fouls": 12.0, "away_fouls": 19.0, "home_tackles": 88.2, "away_tackles": 94.4, "home_passes": 80.5, "away_passes": 74.1, "home_yellow": 1.0, "away_yellow": 4.0, "home_red": 0.0, "away_red": 0.0, "home_players": "gregor-kobel,konstantinos-mavropanos,waldemar-anton,marc-oliver-kempf,silla-wamangituka,wataru-endo,orel-mangala,borna-sosa,gonzalo-castro,nicolas-gonzalez,sasa-kalajd\u017ei\u0107", "away_players": "robin-zentner,jeremiah-st-juste-315611,stefan-bell,moussa-niakhate,danny-da-costa,dominik-kohr,edimilson-fernandes,phillipp-mwene,danny-latza,robin-quaison,karim-onisiwo", "home_tactic": "3-4-1-2", "away_tactic": "3-4-1-2"}