{"origin": "fussballdaten", "year": 2017, "league_key": "england", "season": "2016/2017", "matchday": "26", "link": "https://www.fussballdaten.de/england/2017/26/watford-westham/", "league_name": "Premier League", "date": "25.02.2017", "home_key": "fc-watford", "home_name": "FC Watford", "home_short": "Watford", "away_key": "west-ham-united", "away_name": "West Ham United", "away_short": "West Ham", "home_goals": "1", "away_goals": "1", "home_goals_ht": "1", "away_goals_ht": "0", "home_possesion": 38.0, "away_possesion": 62.0, "home_attemps": 2.0, "away_attemps": 2.0, "home_missed": 5.0, "away_missed": 6.0, "home_freekicks": 15.0, "away_freekicks": 20.0, "home_corners": 4.0, "away_corners": 6.0, "home_offsite": 2.0, "away_offsite": 2.0, "home_held": 1.0, "away_held": 1.0, "home_fouls": 18.0, "away_fouls": 13.0, "home_rating": 4.0, "away_rating": 3.6, "home_tackles": 45.7, "away_tackles": 54.3, "home_passes": 60.0, "away_passes": 79.9, "home_yellow": 5.0, "away_yellow": 5.0, "home_red": 0.0, "away_red": 1.0, "home_players": "heurelho-gomes,daryl-janmaat,younes-kaboul,miguel-britos-328633,jose-holebas,etienne-capoue,valon-behrami,tom-cleverley,mbaye-niang,troy-deeney,mauro-zarate", "away_players": "darren-randolph,cheikhou-kouyate,jose-fonte,winston-reid,aaron-cresswell,mark-noble,pedro-obiang,sofiane-feghouli,manuel-lanzini,robert-snodgrass,michail-antonio", "home_tactic": "4-3-3", "away_tactic": "4-2-3-1"}