{"origin": "fussballdaten", "year": 2021, "league_key": "2liga", "season": "2020/2021", "matchday": "3", "link": "https://www.fussballdaten.de/2liga/2021/3/hannover-braunschweig/", "league_name": "2. Bundesliga", "date": "03.10.2020", "home_key": "hannover-96", "home_name": "Hannover 96", "home_short": "Hannover", "away_key": "eintracht-braunschweig", "away_name": "Eintracht Braunschweig", "away_short": "Braunschweig", "home_goals": "4", "away_goals": "1", "home_goals_ht": "0", "away_goals_ht": "0", "home_possesion": 60.0, "away_possesion": 40.0, "home_attemps": 7.0, "away_attemps": 3.0, "home_missed": 9.0, "away_missed": 3.0, "home_freekicks": 12.0, "away_freekicks": 14.0, "home_corners": 4.0, "away_corners": 4.0, "home_offsite": 2.0, "away_offsite": 2.0, "home_held": 2.0, "away_held": 3.0, "home_fouls": 12.0, "away_fouls": 10.0, "home_yellow": 2.0, "away_yellow": 3.0, "home_red": 0.0, "away_red": 0.0, "home_players": "michael-esser,kingsley-schindler,marcel-franke,timo-huebers,niklas-hult,genki-haraguchi,dominik-kaiser,mike-frantz,linton-maina,hendrik-weydandt,marvin-ducksch", "away_players": "felix-dornebusch,benjamin-kessel,michael-schultz,dominik-wydra,robin-ziegele,jannis-nikolaou,yassin-ben-balla,fabian-kaufmann,martin-kobylanski,felix-kroos,suleiman-abdullahi", "home_tactic": "4-3-1-2", "away_tactic": "4-2-3-1"}