{"origin": "fussballdaten", "year": 2017, "league_key": "bundesliga", "season": "2016/2017", "matchday": "10", "link": "https://www.fussballdaten.de/bundesliga/2017/10/schalke-bremen/", "league_name": "Bundesliga", "date": "06.11.2016", "home_key": "fc-schalke-04", "home_name": "FC Schalke 04", "home_short": "Schalke", "away_key": "sv-werder-bremen", "away_name": "SV Werder Bremen", "away_short": "Bremen", "home_goals": "3", "away_goals": "1", "home_goals_ht": "2", "away_goals_ht": "1", "home_possesion": 52.0, "away_possesion": 48.0, "home_attemps": 4.0, "away_attemps": 5.0, "home_missed": 11.0, "away_missed": 1.0, "home_freekicks": 15.0, "away_freekicks": 15.0, "home_corners": 3.0, "away_corners": 6.0, "home_offsite": 3.0, "away_offsite": 1.0, "home_held": 4.0, "away_held": 4.0, "home_fouls": 12.0, "away_fouls": 14.0, "home_rating": 2.5, "away_rating": 4.2, "home_tackles": 56.2, "away_tackles": 43.8, "home_passes": 87.0, "away_passes": 83.2, "home_yellow": 2.0, "away_yellow": 3.0, "home_red": 0.0, "away_red": 0.0, "home_players": "ralf-faehrmann,benedikt-hoewedes,naldo,matija-nastasi\u0107,alessandro-schoepf,leon-goretzka,johannes-geis,nabil-bentaleb,sead-kola-scaron-inac,eric-maxim-choupo-moting,max-meyer-50206", "away_players": "felix-wiedwald,theodor-gebre-selassie,milo-scaron-veljkovi\u0107,niklas-moisander,santiago-garcia,thanos-petsos,fin-bartels,clemens-fritz,florian-grillitsch,zlatko-junuzovi\u0107,serge-gnabry", "home_tactic": "3-5-2", "away_tactic": "4-1-4-1"}