{"origin": "fussballdaten", "year": 2023, "league_key": "england", "season": "2022/2023", "matchday": "15", "link": "https://www.fussballdaten.de/england/2023/15/nottingham-brentford/", "league_name": "Premier League", "date": "05.11.2022", "home_key": "nottingham-forest", "home_name": "Nottingham Forest", "home_short": "Nottingham", "away_key": "fc-brentford", "away_name": "FC Brentford", "away_short": "Brentford", "home_goals": "2", "away_goals": "2", "home_goals_ht": "1", "away_goals_ht": "1", "home_possesion": 47.0, "away_possesion": 53.0, "home_attemps": 7.0, "away_attemps": 2.0, "home_missed": 9.0, "away_missed": 5.0, "home_offsite": 0.0, "away_offsite": 2.0, "home_held": 0.0, "away_held": 0.0, "home_fouls": 10.0, "away_fouls": 11.0, "home_passes": 75.7, "away_passes": 76.9, "home_yellow": 2.0, "away_yellow": 2.0, "home_red": 0.0, "away_red": 0.0, "home_players": "dean-henderson,serge-aurier,steve-cook,scott-mckenna,neco-williams,ryan-yates-447776,remo-freuler,cheikhou-kouyate,morgan-gibbs-white,brennan-johnson-447777,emmanuel-dennis", "away_players": "david-raya,mads-roerslev-rasmussen-326326,ben-mee,ethan-pinnock,rico-henry,mathias-jensen,vitaly-janelt,joshua-da-silva,bryan-mbeumo,yoane-wissa,keane-lewis-potter", "home_tactic": "4-3-1-2", "away_tactic": "4-3-3"}