{"origin": "fussballdaten", "year": 2017, "league_key": "2liga", "season": "2016/2017", "matchday": "34", "link": "https://www.fussballdaten.de/2liga/2017/34/stuttgart-kwuerzburg/", "league_name": "2. Bundesliga", "date": "21.05.2017", "home_key": "vfb-stuttgart", "home_name": "VfB Stuttgart", "home_short": "Stuttgart", "away_key": "kickers-wuerzburg", "away_name": "Kickers W\u00fcrzburg", "away_short": "K. W\u00fcrzburg", "home_goals": "4", "away_goals": "1", "home_goals_ht": "1", "away_goals_ht": "0", "home_possesion": 56.0, "away_possesion": 44.0, "home_attemps": 7.0, "away_attemps": 5.0, "home_missed": 6.0, "away_missed": 5.0, "home_freekicks": 16.0, "away_freekicks": 17.0, "home_corners": 5.0, "away_corners": 3.0, "home_offsite": 1.0, "away_offsite": 1.0, "home_held": 4.0, "away_held": 3.0, "home_fouls": 16.0, "away_fouls": 16.0, "home_yellow": 0.0, "away_yellow": 2.0, "home_red": 0.0, "away_red": 0.0, "home_players": "mitch-langerak,benjamin-pavard,timo-baumgartl,marcin-kami\u0144ski,emiliano-insua,christian-gentner,matthias-zimmermann,daniel-ginczek,alexandru-maxim,josip-brekalo,simon-terodde", "away_players": "joerg-siebenhandl,clemens-schoppenhauer,sebastian-neumann,david-pisot,tobias-schrock,rico-benatelli,emanuel-taffertshofer,peter-kurzweg,sebastian-ernst,nejmeddin-daghfous,ioannis-karsanidis", "home_tactic": "4-2-3-1", "away_tactic": "3-4-3"}