{"origin": "fussballdaten", "year": 2018, "league_key": "frankreich", "season": "2017/2018", "matchday": "11", "link": "https://www.fussballdaten.de/frankreich/2018/11/guingamp-amiens/", "league_name": "Ligue 1", "date": "28.10.2017", "home_key": "ea-guingamp", "home_name": "EA Guingamp", "home_short": "Guingamp", "away_key": "sc-amiens", "away_name": "SC Amiens", "away_short": "Amiens", "home_goals": "1", "away_goals": "1", "home_goals_ht": "1", "away_goals_ht": "1", "home_possesion": 59.0, "away_possesion": 41.0, "home_attemps": 5.0, "away_attemps": 1.0, "home_missed": 7.0, "away_missed": 5.0, "home_freekicks": 21.0, "away_freekicks": 20.0, "home_corners": 5.0, "away_corners": 5.0, "home_offsite": 5.0, "away_offsite": 1.0, "home_held": 0.0, "away_held": 0.0, "home_fouls": 15.0, "away_fouls": 20.0, "home_rating": 3.5, "away_rating": 4.1, "home_tackles": 48.8, "away_tackles": 51.2, "home_passes": 79.4, "away_passes": 56.4, "home_yellow": 1.0, "away_yellow": 4.0, "home_red": 0.0, "away_red": 1.0, "home_players": "karl-johan-johnsson,jonathan-martins-pereira,christophe-kerbrat,felix-eboa-eboa,franck-tabanou,ludovic-blas,etienne-didot,mustapha-diallo,abdoul-camara,jimmy-briand,nicolas-benezet", "away_players": "regis-gurtner,oualid-el-hajjam,prince-gouano,khaled-adenon-337751,danilo-avelar,serge-gakpe,bongani-zungu,thomas-monconduit,harisson-manzala,gael-kakuta,lacina-traore", "home_tactic": "4-3-3", "away_tactic": "4-4-1-1"}