{"origin": "fussballdaten", "year": 2022, "league_key": "england", "season": "2021/2022", "matchday": "33", "link": "https://www.fussballdaten.de/england/2022/33/tottenham-brighton/", "league_name": "Premier League", "date": "16.04.2022", "home_key": "tottenham-hotspur", "home_name": "Tottenham Hotspur", "home_short": "Tottenham", "away_key": "brighton-and-hove-albion", "away_name": "Brighton and Hove Albion", "away_short": "Brighton", "home_goals": "0", "away_goals": "1", "home_goals_ht": "0", "away_goals_ht": "0", "home_possesion": 49.0, "away_possesion": 51.0, "home_attemps": 0.0, "away_attemps": 5.0, "home_missed": 5.0, "away_missed": 7.0, "home_offsite": 0.0, "away_offsite": 3.0, "home_held": 3.0, "away_held": 3.0, "home_fouls": 14.0, "away_fouls": 10.0, "home_passes": 81.9, "away_passes": 84.0, "home_yellow": 3.0, "away_yellow": 3.0, "home_red": 0.0, "away_red": 0.0, "home_players": "hugo-lloris,cristian-romero,eric-dier,ben-davies,emerson-aparecido-leite-de-souza-junior,rodrigo-bentancur,pierre-emile-hojbjerg,reguilon,dejan-kulusevski,harry-kane,heung-min-son", "away_players": "robert-sanchez,joel-veltman,lewis-dunk,cucurella,tariq-lamptey,pascal-gross,yves-bissouma,moises-caicedo-corozo,leandro-trossard,enock-mwepu,alexis-mac-allister", "home_tactic": "3-4-3", "away_tactic": "3-5-2"}