{"origin": "fussballdaten", "year": 2018, "league_key": "2liga", "season": "2017/2018", "matchday": "17", "link": "https://www.fussballdaten.de/2liga/2018/17/aue-darmstadt/", "league_name": "2. Bundesliga", "date": "08.12.2017", "home_key": "fc-erzgebirge-aue", "home_name": "FC Erzgebirge Aue", "home_short": "Aue", "away_key": "sv-darmstadt-98", "away_name": "SV Darmstadt 98", "away_short": "Darmstadt", "home_goals": "1", "away_goals": "0", "home_goals_ht": "1", "away_goals_ht": "0", "home_possesion": 42.0, "away_possesion": 58.0, "home_attemps": 4.0, "away_attemps": 2.0, "home_missed": 4.0, "away_missed": 3.0, "home_freekicks": 18.0, "away_freekicks": 18.0, "home_corners": 8.0, "away_corners": 5.0, "home_offsite": 0.0, "away_offsite": 0.0, "home_held": 2.0, "away_held": 3.0, "home_fouls": 18.0, "away_fouls": 16.0, "home_yellow": 0.0, "away_yellow": 4.0, "home_red": 0.0, "away_red": 0.0, "home_players": "martin-maennel,fabian-kalig,dominik-wydra,dennis-kempe,malcolm-cacutalua,christian-tiffert,john-patrick-strauss,cebio-soukou,albert-bunjaku,mario-kvesic,dimitrij-nazarov", "away_players": "daniel-fernandes-322083,markus-steinhoefer,immanuel-hoehn,aytac-sulu,fabian-holland,wilson-kamavuaka,hamit-altintop,tobias-kempe,marvin-mehlem,kevin-grosskreutz,terrence-boyd", "home_tactic": "3-4-3", "away_tactic": "4-2-3-1"}