{"origin": "fussballdaten", "year": 2021, "league_key": "2liga", "season": "2020/2021", "matchday": "15", "link": "https://www.fussballdaten.de/2liga/2021/15/karlsruhe-fuerth/", "league_name": "2. Bundesliga", "date": "08.01.2021", "home_key": "karlsruher-sc", "home_name": "Karlsruher SC", "home_short": "Karlsruhe", "away_key": "spvgg-greuther-fuerth", "away_name": "SpVgg Greuther F\u00fcrth", "away_short": "F\u00fcrth", "home_goals": "3", "away_goals": "2", "home_goals_ht": "2", "away_goals_ht": "2", "home_possesion": 52.0, "away_possesion": 48.0, "home_attemps": 6.0, "away_attemps": 7.0, "home_missed": 3.0, "away_missed": 5.0, "home_freekicks": 15.0, "away_freekicks": 15.0, "home_corners": 6.0, "away_corners": 5.0, "home_offsite": 3.0, "away_offsite": 3.0, "home_held": 5.0, "away_held": 3.0, "home_fouls": 12.0, "away_fouls": 15.0, "home_yellow": 3.0, "away_yellow": 3.0, "home_red": 0.0, "away_red": 0.0, "home_players": "paul-seguin,marius-gersbeck,marco-thiede,robin-bormuth,christoph-kobald,philip-heise,marvin-wanitzek,jerome-gondorf,benjamin-goller,kyoung-rok-choi,marc-lorenz", "away_players": "philipp-hofmann,sascha-burchert,marco-meyerhofer,paul-jaeckel,maximilian-bauer-401898,david-raum,anton-stach,paul-seguin,sebastian-ernst,julian-green,jamie-leweling,havard-nielsen", "home_tactic": "4-2-3-1", "away_tactic": "4-1-3-2"}