{"origin": "fussballdaten", "year": 2017, "league_key": "england", "season": "2016/2017", "matchday": "32", "link": "https://www.fussballdaten.de/england/2017/32/palace-arsenal/", "league_name": "Premier League", "date": "10.04.2017", "home_key": "crystal-palace", "home_name": "Crystal Palace", "home_short": "Crystal Palace", "away_key": "fc-arsenal", "away_name": "FC Arsenal", "away_short": "Arsenal", "home_goals": "3", "away_goals": "0", "home_goals_ht": "1", "away_goals_ht": "0", "home_possesion": 41.0, "away_possesion": 59.0, "home_attemps": 7.0, "away_attemps": 3.0, "home_missed": 4.0, "away_missed": 5.0, "home_freekicks": 11.0, "away_freekicks": 16.0, "home_corners": 5.0, "away_corners": 8.0, "home_offsite": 5.0, "away_offsite": 2.0, "home_held": 3.0, "away_held": 3.0, "home_fouls": 11.0, "away_fouls": 9.0, "home_rating": 2.8, "away_rating": 4.0, "home_tackles": 49.2, "away_tackles": 50.8, "home_passes": 63.0, "away_passes": 85.1, "home_yellow": 0.0, "away_yellow": 1.0, "home_red": 0.0, "away_red": 0.0, "home_players": "wilfried-zaha,wayne-hennessey,joel-ward,martin-kelly,mamadou-sakho,jeffrey-schlupp,luka-milivojevi\u0107,yohan-cabaye,jason-puncheon,andros-townsend,christian-benteke", "away_players": "hector-bellerin-moruno,nacho-monreal,shkodran-mustafi,mesut-oezil,granit-xhaka,alexis-sanchez,danny-welbeck,theo-walcott,damian-emiliano-martinez,gabriel-paulista,mohamed-elneny", "home_tactic": "4-2-3-1", "away_tactic": "4-2-3-1"}