{"origin": "fussballdaten", "year": 2021, "league_key": "frankreich", "season": "2020/2021", "matchday": "17", "link": "https://www.fussballdaten.de/frankreich/2021/17/angers-olmarseille/", "league_name": "Ligue 1", "date": "23.12.2020", "home_key": "sco-angers", "home_name": "SCO Angers", "home_short": "Angers", "away_key": "olympique-marseille", "away_name": "Olympique Marseille", "away_short": "Ol. Marseille", "home_goals": "2", "away_goals": "1", "home_goals_ht": "2", "away_goals_ht": "0", "home_possesion": 38.0, "away_possesion": 62.0, "home_attemps": 2.0, "away_attemps": 2.0, "home_missed": 3.0, "away_missed": 3.0, "home_freekicks": 17.0, "away_freekicks": 13.0, "home_corners": 2.0, "away_corners": 8.0, "home_offsite": 2.0, "away_offsite": 2.0, "home_held": 1.0, "away_held": 0.0, "home_fouls": 11.0, "away_fouls": 16.0, "home_yellow": 2.0, "away_yellow": 4.0, "home_red": 0.0, "away_red": 0.0, "home_players": "dimitri-payet,paul-bernardoni,vincent-manceau,ismael-traore-47527,romain-thomas,souleyman-doumbia,lassana-coulibaly,thomas-mangani,mathias-lage,angelo-fulgini,pierrick-capelle", "away_players": "lois-diony,steve-mandanda,alvaro-gonzalez-soberon,boubacar-kamara,duje-\u0106aleta-car,hiroki-sakai,michael-cuisance,valentin-rongier,dimitri-payet,yuto-nagatomo,valere-germain,dario-benedetto", "home_tactic": "4-2-3-1", "away_tactic": "3-5-2"}