{"origin": "fussballdaten", "year": 2022, "league_key": "spanien", "season": "2021/2022", "matchday": "38", "link": "https://www.fussballdaten.de/spanien/2022/38/vallecano-levante/", "league_name": "Primera Divisi\u00f3n", "date": "20.05.2022", "home_key": "rayo-vallecano", "home_name": "Rayo Vallecano", "home_short": "Vallecano", "away_key": "levante-ud", "away_name": "Levante UD", "away_short": "Levante", "home_goals": "2", "away_goals": "4", "home_goals_ht": "1", "away_goals_ht": "3", "home_possesion": 56.0, "away_possesion": 44.0, "home_attemps": 8.0, "away_attemps": 8.0, "home_missed": 13.0, "away_missed": 7.0, "home_offsite": 5.0, "away_offsite": 0.0, "home_held": 2.0, "away_held": 2.0, "home_fouls": 8.0, "away_fouls": 12.0, "home_passes": 81.2, "away_passes": 76.2, "home_yellow": 0.0, "away_yellow": 3.0, "home_red": 0.0, "away_red": 0.0, "home_players": "luca-zidane,ivan-balliu,mario-suarez,alejandro-catena,kevin-rodrigues,unai-lopez,oscar-valentin,bebe,randy-nteka,alvaro-garcia,sergi-guardiola", "away_players": "dani-cardenas,coke,postigo,roberto-suarez-pier,marcelo-saracchi,jose-luis-morales-nogales,melero,nemanja-radoja,enis-bardhi,cantero,roger-marti", "home_tactic": "4-2-3-1", "away_tactic": "4-4-2"}