{"origin": "fussballdaten", "year": 2019, "league_key": "england", "season": "2018/2019", "matchday": "20", "link": "https://www.fussballdaten.de/england/2019/20/liverpool-arsenal/", "league_name": "Premier League", "date": "29.12.2018", "home_key": "fc-liverpool", "home_name": "FC Liverpool", "home_short": "Liverpool", "away_key": "fc-arsenal", "away_name": "FC Arsenal", "away_short": "Arsenal", "home_goals": "5", "away_goals": "1", "home_goals_ht": "4", "away_goals_ht": "1", "home_possesion": 66.0, "away_possesion": 34.0, "home_attemps": 10.0, "away_attemps": 3.0, "home_missed": 3.0, "away_missed": 3.0, "home_freekicks": 16.0, "away_freekicks": 10.0, "home_corners": 5.0, "away_corners": 3.0, "home_offsite": 2.0, "away_offsite": 5.0, "home_held": 2.0, "away_held": 2.0, "home_fouls": 8.0, "away_fouls": 11.0, "home_rating": 3.0, "away_rating": 4.3, "home_tackles": 56.5, "away_tackles": 43.5, "home_passes": 81.7, "away_passes": 82.9, "home_yellow": 1.0, "away_yellow": 2.0, "home_red": 0.0, "away_red": 0.0, "home_players": "alisson,trent-alexander-arnold,dejan-lovren,virgil-van-dijk,andrew-robertson,georginio-wijnaldum,fabio-henrique-tavares,xherdan-shaqiri,roberto-firmino,sadio-mane,mohamed-salah", "away_players": "bernd-leno,stephan-lichtsteiner,sokratis,shkodran-mustafi,ainsley-maitland-niles,lucas-torreira,granit-xhaka,sead-kola-scaron-inac,aaron-ramsey,pierre-emerick-aubameyang,alex-iwobi", "home_tactic": "4-2-3-1", "away_tactic": "3-4-3"}