{"origin": "fussballdaten", "year": 2021, "league_key": "england", "season": "2020/2021", "matchday": "13", "link": "https://www.fussballdaten.de/england/2021/13/arsenal-southampton/", "league_name": "Premier League", "date": "16.12.2020", "home_key": "fc-arsenal", "home_name": "FC Arsenal", "home_short": "Arsenal", "away_key": "fc-southampton", "away_name": "FC Southampton", "away_short": "Southampton", "home_goals": "1", "away_goals": "1", "home_goals_ht": "0", "away_goals_ht": "1", "home_possesion": 42.0, "away_possesion": 58.0, "home_attemps": 4.0, "away_attemps": 3.0, "home_missed": 3.0, "away_missed": 6.0, "home_freekicks": 14.0, "away_freekicks": 14.0, "home_corners": 2.0, "away_corners": 7.0, "home_offsite": 1.0, "away_offsite": 1.0, "home_held": 4.0, "away_held": 4.0, "home_fouls": 13.0, "away_fouls": 13.0, "home_tackles": 92.3, "away_tackles": 91.7, "home_passes": 88.3, "away_passes": 80.7, "home_yellow": 2.0, "away_yellow": 3.0, "home_red": 1.0, "away_red": 0.0, "home_players": "bernd-leno,ainsley-maitland-niles,rob-holding,gabriel-dos-santos-magalhaes,kieran-tierney,mohamed-elneny,dani-ceballos,nicolas-pepe,edward-nketiah,bukayo-saka,pierre-emerick-aubameyang", "away_players": "alex-mccarthy,kyle-walker-peters,jan-bednarek,jannik-vestergaard,ryan-bertrand,stuart-armstrong,james-ward-prowse,oriol-romeu,theo-walcott,danny-ings,che-adams", "home_tactic": "4-2-3-1", "away_tactic": "4-4-2"}