{"origin": "fussballdaten", "year": 2023, "league_key": "frankreich", "season": "2022/2023", "matchday": "10", "link": "https://www.fussballdaten.de/frankreich/2023/10/lille-lens/", "league_name": "Ligue 1", "date": "09.10.2022", "home_key": "osc-lille", "home_name": "OSC Lille", "home_short": "Lille", "away_key": "rc-lens", "away_name": "RC Lens", "away_short": "Lens", "home_goals": "1", "away_goals": "0", "home_goals_ht": "1", "away_goals_ht": "0", "home_possesion": 45.0, "away_possesion": 55.0, "home_attemps": 6.0, "away_attemps": 2.0, "home_missed": 6.0, "away_missed": 8.0, "home_offsite": 0.0, "away_offsite": 2.0, "home_held": 3.0, "away_held": 3.0, "home_fouls": 0.0, "away_fouls": 1.0, "home_passes": 81.4, "away_passes": 83.8, "home_yellow": 3.0, "away_yellow": 5.0, "home_red": 0.0, "away_red": 0.0, "home_players": "lucas-chevalier,bafode-diakite,jose-fonte,tiago-djalo,ismaily-254269,benjamin-andre,andre-gomes,adam-ounas,angel-gomes,jonathan-bamba,jonathan-david", "away_players": "brice-samba,massadio-haidara,kevin-danso,facundo-medina,jimmy-cabot,salis-abdul-samed,seko-fofana,deiver-machado,florian-sotoca,david-costa,lois-openda,florian-sotoca", "home_tactic": "4-2-3-1", "away_tactic": "3-4-2-1"}